implicitdict/__init__.py
implicitdict/_version.py
implicitdict/jsonschema.py
implicitdict-4.1.0.dist-info/licenses/LICENSE.md
implicitdict-4.1.0.dist-info/METADATA
implicitdict-4.1.0.dist-info/WHEEL
implicitdict-4.1.0.dist-info/top_level.txt
implicitdict-4.1.0.dist-info/RECORD
