Metadata-Version: 2.4
Name: implicitdict
Version: 4.1.0
Summary: ImplicitDict base class that turns a subclass into a dict indexing attributes, making [de]serialization easy for complex typing-annotated data types.
Author-email: InterUSS Platform <tsc@lists.interussplatform.org>
License-Expression: Apache-2.0
Project-URL: Homepage, https://github.com/interuss/implicitdict
Project-URL: Bug Tracker, https://github.com/interuss/implicitdict/issues
Classifier: Programming Language :: Python :: 3
Classifier: Operating System :: OS Independent
Requires-Python: >=3.11
License-File: LICENSE.md
Requires-Dist: arrow
Requires-Dist: jsonschema
Requires-Dist: pytimeparse
Dynamic: license-file
